py_model/__version__.py
py_model-0.0.1.dist-info/DESCRIPTION.rst
py_model-0.0.1.dist-info/METADATA
py_model-0.0.1.dist-info/RECORD
py_model-0.0.1.dist-info/WHEEL
py_model-0.0.1.dist-info/metadata.json
py_model-0.0.1.dist-info/top_level.txt
